cloudshell_user_sync/__init__.py
cloudshell_user_sync/cli.py
cloudshell_user_sync/exceptions.py
cloudshell_user_sync/actions/__init__.py
cloudshell_user_sync/actions/cloudshell_sync.py
cloudshell_user_sync/actions/ldap_pull.py
cloudshell_user_sync/commands/__init__.py
cloudshell_user_sync/commands/run_scheduler.py
cloudshell_user_sync/commands/set_config.py
cloudshell_user_sync/commands/set_credential.py
cloudshell_user_sync/commands/set_mapping.py
cloudshell_user_sync/commands/sync_groups.py
cloudshell_user_sync/models/__init__.py
cloudshell_user_sync/models/config.py
cloudshell_user_sync/models/cs_import.py
cloudshell_user_sync/utility/__init__.py
cloudshell_user_sync/utility/config_handler.py
cloudshell_user_sync/utility/keyring_handler.py
cloudshell_user_sync/utility/ldap3_handler.py
cloudshell_user_sync/utility/path_helper.py
cloudshell_user_sync/utility/rotating_log_handler.py
cloudshell_user_sync/utility/safe_echo.py
cloudshell_user_sync/utility/schedule_handler.py
cloudshell_user_sync-0.5.0.dist-info/LICENSE
cloudshell_user_sync-0.5.0.dist-info/METADATA
cloudshell_user_sync-0.5.0.dist-info/WHEEL
cloudshell_user_sync-0.5.0.dist-info/entry_points.txt
cloudshell_user_sync-0.5.0.dist-info/top_level.txt
cloudshell_user_sync-0.5.0.dist-info/RECORD
