Metadata-Version: 2.1
Name: cloudshell-user-sync
Version: 0.5.0
Summary: sync Cloudshell groups with AD Groups
Home-page: https://github.com/QualiSystemsLab/cloudshell-user-sync
Author: QualiLab
Author-email: support@quali.com
License: MIT
Classifier: Programming Language :: Python :: 3.9
Classifier: License :: OSI Approved :: MIT License
Classifier: Operating System :: OS Independent
Requires-Python: >=3.9
License-File: LICENSE
Requires-Dist: cloudshell-automation-api
Requires-Dist: ldap3
Requires-Dist: click
Requires-Dist: schedule
Requires-Dist: dacite
Requires-Dist: keyring
Requires-Dist: pywin32 ; platform_system == "Windows"
